<?xml version="1.0" encoding="UTF-8"?>
<!--Sample XML file generated by XMLSpy v2008 sp1 (http://www.altova.com)-->
<study gridId="db762d64-e213-4bf9-9f9b-bccd36be56e7" version="0" xsi:schemaLocation="gme://ccts.cabig/1.0/gov.nih.nci.cabig.ccts.domain ccts-domain.xsd" xmlns="gme://ccts.cabig/1.0/gov.nih.nci.cabig.ccts.domain" xmlns:xsi="http://www.w3.org/2001/XMLSchema-instance">
	<blindedIndicator>False</blindedIndicator>
	<multiInstitutionIndicator>String</multiInstitutionIndicator>
	<randomizedIndicator>false</randomizedIndicator>
	<shortTitleText>Combination Chemotherapy NHL</shortTitleText>
	<longTitleText>RANDOMIZED PHASE I/II STUDY OF VACCINIA-CEA(6D)-TRICOM AND FOWLPOX-(6D)-TRICOM WITH GM-CSF IN COMBINATION WITH DOCETAXEL IN PATIENTS WITH CEA-BEARING CANCERS</longTitleText>
	<descriptionText>Test</descriptionText>
	<precisText>Test</precisText>
	<phaseCode>Test</phaseCode>
	<dataEntryStatus>INCOMPLETE</dataEntryStatus>
	<coordinatingCenterStudyStatus>ACTIVE</coordinatingCenterStudyStatus>
	<type>Test</type>
	<primaryIdentifier>Test</primaryIdentifier>
	<targetAccrualNumber>0</targetAccrualNumber>
	<identifier xsi:type="OrganizationAssignedIdentifierType">
		<source>String</source>
		<type>Coordinating Center Identifier</type>
		<value>CDR0000078234</value>
		<primaryIndicator>true</primaryIndicator>
		<systemName>Test</systemName>
	</identifier>
	<treatmentEpoch>
		<name>Drug Treatment</name>
		<descriptionText>Test</descriptionText>
		<arm gridId="de3a0ef0-1f02-4da6-afdc-cc9042cdb594">
			<name>Arm</name>
			<descriptionText>Arm Test</descriptionText>
			<targetAccrualNumber>300</targetAccrualNumber>
		</arm>
		<eligibilityCriteria>
			<notApplicableIndicator>true</notApplicableIndicator>
			<questionNumber>test</questionNumber>
			<questionText>test</questionText>
		</eligibilityCriteria>
		<stratificationCriteria>
			<questionNumber>0</questionNumber>
			<questionText>Test</questionText>
			<permissibleAnswer>
				<permissibleAnswer>Test</permissibleAnswer>
			</permissibleAnswer>
		</stratificationCriteria>
	</treatmentEpoch>
	<studyFundingSponsor>
		<healthcareSite gridId="WF GRID ID">
			<name>Test</name>
			<descriptionText>Test</descriptionText>
			<address>
				<streetAddress>Test</streetAddress>
				<city>Test</city>
				<stateCode>Test</stateCode>
				<postalCode>Test</postalCode>
				<countryCode>Test</countryCode>
			</address>
			<nciInstituteCode>Wake</nciInstituteCode>
		</healthcareSite>
	</studyFundingSponsor>
	<studyDisease>
		<leadDisease>true</leadDisease>
		<diseaseTerm>
			<term>Test</term>
			<ctepTerm>Test</ctepTerm>
			<medraCode>Test</medraCode>
		</diseaseTerm>
	</studyDisease>
</study>
